taeper/__init__.py
taeper/cli.py
taeper/taeper.py
taeper-0.1.0.dist-info/DESCRIPTION.rst
taeper-0.1.0.dist-info/METADATA
taeper-0.1.0.dist-info/RECORD
taeper-0.1.0.dist-info/WHEEL
taeper-0.1.0.dist-info/entry_points.txt
taeper-0.1.0.dist-info/metadata.json
taeper-0.1.0.dist-info/top_level.txt
