Metadata-Version: 2.0
Name: taeper
Version: 0.1.0
Summary: Simulate repeating a nanopore experiment.
Home-page: https://github.com/mbhall88/taeper
Author: Michael Hall
Author-email: mbhall88@gmail.com
License: MIT license
Keywords: taeper
Platform: UNKNOWN
Classifier: License :: OSI Approved :: MIT License
Classifier: Natural Language :: English
Classifier: Programming Language :: Python :: 3.5
Classifier: Programming Language :: Python :: 3.6
Requires-Dist: ont-fast5-api
Requires-Dist: numpy
